linear/__init__.py
linear/ai/claude.py
linear/api/__init__.py
linear/api/attachments.py
linear/api/client.py
linear/api/comments.py
linear/api/cycles.py
linear/api/issues.py
linear/api/labels.py
linear/api/projects.py
linear/api/roadmaps.py
linear/api/teams.py
linear/api/users.py
linear/cli.py
linear/commands/__init__.py
linear/commands/attachments.py
linear/commands/comments.py
linear/commands/cycles.py
linear/commands/issues.py
linear/commands/labels.py
linear/commands/projects.py
linear/commands/roadmaps.py
linear/commands/teams.py
linear/commands/users.py
linear/formatters/__init__.py
linear/formatters/attachments.py
linear/formatters/base.py
linear/formatters/comments.py
linear/formatters/cycles.py
linear/formatters/issues.py
linear/formatters/labels.py
linear/formatters/projects.py
linear/formatters/roadmaps.py
linear/formatters/teams.py
linear/formatters/users.py
linear/models/__init__.py
linear/models/attachments.py
linear/models/base.py
linear/models/comments.py
linear/models/cycles.py
linear/models/issues.py
linear/models/labels.py
linear/models/projects.py
linear/models/roadmaps.py
linear/models/teams.py
linear/models/users.py
linear/utils/__init__.py
linear/utils/context.py
linear/utils/editor.py
linear_app-0.0.14.dist-info/WHEEL
linear_app-0.0.14.dist-info/entry_points.txt
linear_app-0.0.14.dist-info/METADATA
linear_app-0.0.14.dist-info/RECORD
