Metadata-Version: 2.3
Name: linear-app
Version: 0.0.14
Summary: Add your description here
Requires-Dist: typer>=0.15.0
Requires-Dist: httpx>=0.28.0
Requires-Dist: rich>=13.0.0
Requires-Dist: pydantic>=2.9.0
Requires-Dist: pyyaml>=6.0.0
Requires-Python: >=3.13
